rtix/__init__.py
rtix/core/__init__.py
rtix/core/exception.py
rtix/core/logging.py
rtix/core/status.py
rtix/core/timer.py
rtix/ipc/__init__.py
rtix/ipc/channel_map.py
rtix/ipc/node.py
rtix/process/__init__.py
rtix/process/process.py
rtix/types/__init__.py
rtix/types/common.proto
rtix/types/common_pb2.py
rtix-0.9.5.dist-info/LICENSE
rtix-0.9.5.dist-info/METADATA
rtix-0.9.5.dist-info/WHEEL
rtix-0.9.5.dist-info/top_level.txt
rtix-0.9.5.dist-info/RECORD
