Metadata-Version: 2.1
Name: rtix
Version: 0.9.5
Summary: Fast and lightweight IPC and orchestration layer for robotics and embodied AI applications.
Author: Velodex Robotics, Inc and RTIX Developers
License-File: LICENSE
Requires-Dist: grpcio>=1.70.0
Requires-Dist: grpcio-tools>=1.70.0
Requires-Dist: pynng>=0.7.1
Requires-Dist: pyyaml>=6.0.2
